README.md
setup.py
apm/APMAgent.py
apm/__init__.py
fynalai_apm_python.egg-info/PKG-INFO
fynalai_apm_python.egg-info/SOURCES.txt
fynalai_apm_python.egg-info/dependency_links.txt
fynalai_apm_python.egg-info/requires.txt
fynalai_apm_python.egg-info/top_level.txt