Metadata-Version: 2.1
Name: fynalai-apm-python
Version: 0.0.5
Summary: Agent Package Manager things
Home-page: https://github.com/fynal-ai/apm/apm-python
Author: fynal-ai
Author-email: fynalgpt@gmail.com
Classifier: Programming Language :: Python :: 3
Classifier: License :: OSI Approved :: MIT License
Classifier: Operating System :: OS Independent
Requires-Dist: requests>=2.16.0
